oewn_core/__init__.py
oewn_core/deserialize.py
oewn_core/normalize.py
oewn_core/serialize.py
oewn_core/wordnet.py
oewn_core/wordnet_fromyaml.py
oewn_core/wordnet_toyaml.py
oewn_core/yaml_to_yaml.py
oewn_syntagnet/__init__.py
oewn_syntagnet/augment_yaml_with_syntagnet.py
oewn_syntagnet/export_syntagnet_to_yaml.py
oewn_syntagnet/inject_syntagnet.py
oewn_validate/__init__.py
oewn_validate/validate.py
oewn_xml/__init__.py
oewn_xml/wordnet_fromxml.py
oewn_xml/wordnet_toxml.py
oewn_xml/wordnet_xml.py
oewn_xml/xml_to_yaml.py
oewn_xml/yaml_to_xml.py
tests/__init__.py
tests/_test_args.py
tests/_test_merge.py
tests/model.py
tests/test_browse.py
tests/test_discriminant.py
tests/test_escapables.py
tests/test_escaping_schemes.py
tests/test_extend.py
tests/test_sensekeys.py
tests/test_transitive.py
tests/test_xml_id_chars.py
tests/test_xml_idness.py
tests/test_xml_ids.py
tests/utils.py
oewn_core-1.3.2.dist-info/METADATA
oewn_core-1.3.2.dist-info/WHEEL
oewn_core-1.3.2.dist-info/top_level.txt
oewn_core-1.3.2.dist-info/RECORD
