Metadata-Version: 2.4
Name: oewn-core
Version: 1.3.2
Summary: Core library for oewn
Home-page: https://github.com/oewntk/oewn-core
Author: Bernard Bou, John McCrae
Author-email: oewntk@gmail.com
License: GPL-3.0
Classifier: Programming Language :: Python :: 3
Classifier: Operating System :: OS Independent
Requires-Python: >=3.9
Requires-Dist: PyYAML
Provides-Extra: dev
Requires-Dist: unittest; extra == "dev"
Dynamic: author
Dynamic: author-email
Dynamic: classifier
Dynamic: description
Dynamic: description-content-type
Dynamic: home-page
Dynamic: license
Dynamic: provides-extra
Dynamic: requires-dist
Dynamic: requires-python
Dynamic: summary
